README.rst
setup.py
disimpy/__init__.py
disimpy/gradients.py
disimpy/simulations.py
disimpy/substrates.py
disimpy/utils.py
disimpy.egg-info/PKG-INFO
disimpy.egg-info/SOURCES.txt
disimpy.egg-info/dependency_links.txt
disimpy.egg-info/requires.txt
disimpy.egg-info/top_level.txt
disimpy/tests/__init__.py
disimpy/tests/cylinder_mesh_closed.pkl
disimpy/tests/cylinder_mesh_open.pkl
disimpy/tests/desired_subvoxel_indices.npy
disimpy/tests/desired_triangle_indices.npy
disimpy/tests/example_mesh.pkl
disimpy/tests/example_traj.txt
disimpy/tests/fibre_mesh.pkl
disimpy/tests/misst_cylinder_signal_smalldelta_1ms_bigdelta_40ms_radius_5um.txt
disimpy/tests/misst_cylinder_signal_smalldelta_30ms_bigdelta_40ms_radius_5um.txt
disimpy/tests/misst_sphere_signal_smalldelta_1ms_bigdelta_40ms_radius_5um.txt
disimpy/tests/misst_sphere_signal_smalldelta_30ms_bigdelta_40ms_radius_5um.txt
disimpy/tests/neuron-model.pkl
disimpy/tests/neuron-model.stl
disimpy/tests/sphere_mesh.pkl
disimpy/tests/test_gradients.py
disimpy/tests/test_simulations.py
disimpy/tests/test_substrates.py
disimpy/tests/test_traj.txt
disimpy/tests/test_utils.py