Metadata-Version: 2.1
Name: disimpy
Version: 0.3.0
Summary: Massively parallel diffusion MR simulator
Home-page: https://github.com/kerkelae/disimpy
Author: Leevi Kerkelä
Author-email: leevi.kerkela@protonmail.com
License: MIT
